img3lib/__init__.py
img3lib/__main__.py
img3lib/der.py
img3lib/img3.py
img3lib/kpwn.py
img3lib/lzsscode.py
img3lib/utils.py
pyimg3lib-1.2.5.dist-info/METADATA
pyimg3lib-1.2.5.dist-info/WHEEL
pyimg3lib-1.2.5.dist-info/RECORD
