Metadata-Version: 2.1
Name: pyimg3lib
Version: 1.2.5
Summary: iOS Image3 lib
Home-page: https://github.com/Merculous/PyImg3lib
Author: Merculous
Author-email: 24739823+Merculous@users.noreply.github.com
Requires-Python: >=3.11,<4.0
Classifier: Programming Language :: Python :: 3
Classifier: Programming Language :: Python :: 3.11
Classifier: Programming Language :: Python :: 3.12
Classifier: Programming Language :: Python :: 3.13
Requires-Dist: asn1 (>=2.7.0,<3.0.0)
Requires-Dist: pycryptodome (>=3.19.0,<4.0.0)
Requires-Dist: pylzss (>=0.3.4,<0.4.0)
Project-URL: Repository, https://github.com/Merculous/PyImg3lib
